xrx_redis_file_transporter/__init__.py
xrx_redis_file_transporter-0.0.12.dist-info/METADATA
xrx_redis_file_transporter-0.0.12.dist-info/WHEEL
xrx_redis_file_transporter-0.0.12.dist-info/top_level.txt
xrx_redis_file_transporter-0.0.12.dist-info/RECORD
