Metadata-Version: 2.1
Name: xrx-redis-file-transporter
Version: 0.0.12
Summary: A redis file transport package
Home-page: UNKNOWN
License: UNKNOWN
Platform: UNKNOWN
Classifier: Programming Language :: Python :: 3
Classifier: License :: OSI Approved :: MIT License
Classifier: Operating System :: OS Independent
Requires-Python: >=3.7
